mximport/__info__.py
mximport/__init__.py
mximport/main.py
mximport-0.1.1.dist-info/METADATA
mximport-0.1.1.dist-info/WHEEL
mximport-0.1.1.dist-info/top_level.txt
mximport-0.1.1.dist-info/RECORD
