Metadata-Version: 2.1
Name: mximport
Version: 0.1.1
Summary: Remove all limits on Python package imports
Home-page: https://github.com/magic-python-toolbox/mximport
Author: DIYer22
Author-email: ylxx@live.com
Classifier: Topic :: Software Development :: Libraries :: Python Modules
Classifier: Programming Language :: Python :: 3
Classifier: License :: OSI Approved :: MIT License
Classifier: Operating System :: OS Independent
